extratools_limit/__init__.py
extratools_limit/py.typed
extratools_limit/rate_limit.py
extratools_limit-0.1.1.dist-info/METADATA
extratools_limit-0.1.1.dist-info/WHEEL
extratools_limit-0.1.1.dist-info/licenses/LICENSE
extratools_limit-0.1.1.dist-info/RECORD
